multi_task_utils/__init__.py
multi_task_utils/multi_task_utils.py
multi_task_utils-0.1.1.dist-info/AUTHORS.rst
multi_task_utils-0.1.1.dist-info/LICENSE
multi_task_utils-0.1.1.dist-info/METADATA
multi_task_utils-0.1.1.dist-info/WHEEL
multi_task_utils-0.1.1.dist-info/top_level.txt
multi_task_utils-0.1.1.dist-info/RECORD
