Metadata-Version: 2.1
Name: multi-task-utils
Version: 0.1.1
Summary: multi-task training utils for pytorch, pytorch-lightning
Home-page: https://github.com/cccntu/multi_task_utils
Author: Jonathan Chang
Author-email: ttjtftx@gmail.com
License: MIT license
Keywords: multi_task_utils
Platform: UNKNOWN
Classifier: Development Status :: 2 - Pre-Alpha
Classifier: Intended Audience :: Developers
Classifier: License :: OSI Approved :: MIT License
Classifier: Natural Language :: English
Classifier: Programming Language :: Python :: 3
Classifier: Programming Language :: Python :: 3.5
Classifier: Programming Language :: Python :: 3.6
Classifier: Programming Language :: Python :: 3.7
Classifier: Programming Language :: Python :: 3.8
Requires-Python: >=3.5
Requires-Dist: torch
Requires-Dist: pytorch-lightning
